pktype/__init__.py
pktype/pokemon_type.py
pktype/type_file.py
pkTypeCheker-0.0.1.post2302071231.dist-info/METADATA
pkTypeCheker-0.0.1.post2302071231.dist-info/WHEEL
pkTypeCheker-0.0.1.post2302071231.dist-info/top_level.txt
pkTypeCheker-0.0.1.post2302071231.dist-info/zip-safe
pkTypeCheker-0.0.1.post2302071231.dist-info/RECORD
