Metadata-Version: 2.1
Name: pkTypeCheker
Version: 0.0.1-2302071231
Summary: A library for checking Pokemon type compatibility
Home-page: https://twitter.com/qr1x_while :
Author: roa0831
Author-email: 
License: MIT
Classifier: Programming Language :: Python :: 3.7
